narf/__init__.py
narf/data/__init__.py
narf/data/generate.py
narf/data/loaders/__init__.py
narf/data/loaders/base_loader.py
narf/data/loaders/base_spec.py
narf/data/loaders/binance/__init__.pyi
narf/data/loaders/binance_vision/__init__.py
narf/data/loaders/binance_vision/__init__.pyi
narf/data/loaders/binance_vision/loader.py
narf/data/loaders/binance_vision/spec.py
narf-0.1.2.dist-info/METADATA
narf-0.1.2.dist-info/WHEEL
narf-0.1.2.dist-info/top_level.txt
narf-0.1.2.dist-info/RECORD
