Metadata-Version: 2.4
Name: narf
Version: 0.1.2
Summary: Market data loader library for cryptocurrency exchanges
Project-URL: Homepage, https://github.com/numan-narf/narf-market-data
Project-URL: Repository, https://github.com/numan-narf/narf-market-data
Project-URL: Issues, https://github.com/numan-narf/narf-market-data/issues
Requires-Python: >=3.12
Requires-Dist: build>=1.3.0
Requires-Dist: matplotlib>=3.10.7
Requires-Dist: pandas>=2.3.3
Requires-Dist: pandas-stubs>=2.3.2.250926
Requires-Dist: requests>=2.32.5
Requires-Dist: twine>=6.2.0
Requires-Dist: types-requests>=2.32.4.20250913
Requires-Dist: bump2version>=1.0.1
